README
setup.py
memcachelock/__init__.py
memcachelock.egg-info/PKG-INFO
memcachelock.egg-info/SOURCES.txt
memcachelock.egg-info/dependency_links.txt
memcachelock.egg-info/requires.txt
memcachelock.egg-info/top_level.txt
memcachelock.egg-info/zip-safe