Metadata-Version: 1.1
Name: memcachelock
Version: 0.2
Summary: Use memcache as a lock server
Home-page: http://github.com/vpelletier/python-memcachelock
Author: Vincent Pelletier
Author-email: plr.vincent@gmail.com
License: GPL
Keywords: memcache lock
Platform: any
Classifier: Intended Audience :: Developers
Classifier: License :: OSI Approved :: GNU General Public License (GPL)
Classifier: Operating System :: OS Independent
